langchain_nomic/__init__.py
langchain_nomic/embeddings.py
langchain_nomic/py.typed
gigachain_nomic-0.1.2.dist-info/LICENSE
gigachain_nomic-0.1.2.dist-info/METADATA
gigachain_nomic-0.1.2.dist-info/WHEEL
gigachain_nomic-0.1.2.dist-info/RECORD
