Metadata-Version: 2.1
Name: gigachain-nomic
Version: 0.1.2
Summary: An integration package connecting Nomic and GigaChain
Home-page: https://github.com/ai-forever/gigachain
License: MIT
Requires-Python: >=3.8.1,<4.0
Classifier: License :: OSI Approved :: MIT License
Classifier: Programming Language :: Python :: 3
Classifier: Programming Language :: Python :: 3.9
Classifier: Programming Language :: Python :: 3.10
Classifier: Programming Language :: Python :: 3.11
Classifier: Programming Language :: Python :: 3.12
Requires-Dist: gigachain-core (>=0.1.46,<0.3)
Requires-Dist: nomic (>=3.0.29,<4.0.0)
Requires-Dist: pillow (>=10.3.0,<11.0.0)
Project-URL: Repository, https://github.com/ai-forever/gigachain
Project-URL: Source Code, https://github.com/ai-forever/gigachain/tree/master/libs/partners/nomic
